src/Full_Adder.sv
// Full Adder single bit

module Full_Adder (
    input logic A, B,
    input logic cin,

    output logic sum, cout
);
    
    assign sum = A ^ B ^ cin;
    assign cout = (A & B) | (B & cin) | (A & cin);
endmodule

src/Full_Adder_32bit.sv
// Full Adder 32-bit

module Full_Adder_32bit (
    input logic [31:0] A, B,
    input logic cin,

    output logic [31:0] sum,
    output logic cout
);

logic [32:0] carry;
assign carry[0] = cin;

    genvar i;
    generate
        for (i = 0; i < 32; i++) 
        begin : full_adder_32bit

            Full_Adder FA32 (
                .A(A[i]),
                .B(B[i]),
                .cin(carry[i]),
                .sum(sum[i]),
                .cout(carry[i+1])
            );
        end
    endgenerate

    assign cout = carry[32];
endmodule

src/ALU_32bit.sv
module ALU_32bit (
    input logic [31:0] A, B,
    input logic [3:0] opcode,
    input logic carry_in,
    output logic [31:0] result,
    output logic zero, carry_out, overflow, negative
);

localparam ADD_OP  = 4'b0000,
           SUB_OP  = 4'b1000,
           AND_OP  = 4'b0111,
           OR_OP   = 4'b0110,
           XOR_OP  = 4'b0100,
           SLL_OP  = 4'b0001,
           SRL_OP  = 4'b0101, 
           SRA_OP  = 4'b1101,
           SLT_OP  = 4'b0010,
           SLTU_OP = 4'b0011;           

logic [31:0] B_operated;
logic [32:0] add_result;
assign B_operated = (opcode == SUB_OP) ? ~B : B;

// Perform addition or subtraction
Full_Adder_32bit FA32 (
    .A(A),
    .B(B_operated),
    .cin(carry_in),
    .sum(add_result[31:0]),
    .cout(add_result[32])
);

// Determine result based on opcode
always_comb begin
    case (opcode)
        ADD_OP, SUB_OP: result = add_result[31:0] ;
        AND_OP: result = A & B;
        OR_OP: result = A | B;
        XOR_OP: result = A ^ B;
        SLL_OP: result = A << B[4:0];
        SRL_OP: result = A >> B[4:0];
        SRA_OP: result = $signed(A) >>> B[4:0];
        SLT_OP: result = ($signed(A) < $signed(B)) ? 32'b1 : 32'b0;
        SLTU_OP: result = (A < B) ? 32'b1 : 32'b0;
        default: result = 32'b0;
    endcase
end

// Set flags
assign zero = (result == 32'b0);
assign carry_out = ((opcode == ADD_OP) || (opcode == SUB_OP)) ? add_result[32] : 1'b0;
assign overflow = ((opcode == ADD_OP) || (opcode == SUB_OP)) ? ((A[31] == B_operated[31]) && (result[31] != A[31])) : 1'b0;
assign negative = result[31];

endmodule

tb/ALU_tb.sv
module ALU_tb ();

    logic [31:0] A, B;
    logic [3:0]  opcode;
    logic        carry_in;
    logic [31:0] result;
    logic        zero, carry_out, overflow, negative;

    // Instantiate the ALU
    ALU_32bit DUT (
        .A(A),
        .B(B),
        .opcode(opcode),
        .carry_in(carry_in),
        .result(result),
        .carry_out(carry_out),
        .zero(zero),
        .overflow(overflow),
        .negative(negative)
    );

    initial begin
        // Enable waveform dumping for GTKWave
        $dumpfile("alu_waves.vcd");
        $dumpvars(0, ALU_tb);

        $display("--- STARTING ALU STRESS TEST ---");

        // 1. Test ADD (Opcode: 4'b0000)
        A = 32'd15; B = 32'd10; opcode = 4'b0000; carry_in = 0; 
        #10; 
        $display("ADD (0000): %d + %d = %d", A, B, result);

        // 2. Test SUB (Opcode: 4'b1000)
        A = 32'd25; B = 32'd10; opcode = 4'b1000; carry_in = 1; // carry_in = 1 for 2's complement sub
        #10; 
        $display("SUB (1000): %d - %d = %d", A, B, result);

        // 3. Test AND (Opcode: 4'b0111)
        A = 32'b1100; B = 32'b1010; opcode = 4'b0111; carry_in = 0; 
        #10; 
        $display("AND (0111): %b & %b = %b", A[3:0], B[3:0], result[3:0]);

        // 4. Test OR (Opcode: 4'b0110)
        A = 32'b1100; B = 32'b1010; opcode = 4'b0110; carry_in = 0; 
        #10; 
        $display("OR  (0110): %b | %b = %b", A[3:0], B[3:0], result[3:0]);

        // 5. Test XOR (Opcode: 4'b0100)
        A = 32'b1100; B = 32'b1010; opcode = 4'b0100; carry_in = 0; 
        #10; 
        $display("XOR (0100): %b ^ %b = %b", A[3:0], B[3:0], result[3:0]);

        // 6. Test Shift Left Logical (Opcode: 4'b0001)
        A = 32'd15; B = 32'd2; opcode = 4'b0001; carry_in = 0; 
        #10; 
        $display("SLL (0001): 15 << 2 = %d", result);

        // 7. Test Set Less Than (SLT - Opcode: 4'b0010)
        A = -32'd5; B = 32'd10; opcode = 4'b0010; carry_in = 0; 
        #10; 
        $display("SLT (0010): -5 < 10 = %d (1 means True)", result);

        // 8. Test Zero Flag (Using SUB)
        A = 32'd42; B = 32'd42; opcode = 4'b1000; carry_in = 1; 
        #10; 
        $display("ZERO TEST : %d - %d = %d | Zero Flag: %b", A, B, result, zero);

        $display("--- TEST COMPLETE ---");
        $finish;
    end
endmodule

docs/alu_waves.vcd
$version Generated by VerilatedVcd $end
$timescale 1ps $end
 $scope module TOP $end
  $scope module ALU_tb $end
   $var wire 32 # A [31:0] $end
   $var wire 32 $ B [31:0] $end
   $var wire 4 % opcode [3:0] $end
   $var wire 1 & carry_in $end
   $var wire 32 l result [31:0] $end
   $var wire 1 m zero $end
   $var wire 1 G carry_out $end
   $var wire 1 H overflow $end
   $var wire 1 n negative $end
   $scope module DUT $end
    $var wire 32 # A [31:0] $end
    $var wire 32 $ B [31:0] $end
    $var wire 4 % opcode [3:0] $end
    $var wire 1 & carry_in $end
    $var wire 32 l result [31:0] $end
    $var wire 1 m zero $end
    $var wire 1 G carry_out $end
    $var wire 1 H overflow $end
    $var wire 1 n negative $end
    $var wire 4 T! ADD_OP [3:0] $end
    $var wire 4 U! SUB_OP [3:0] $end
    $var wire 4 V! AND_OP [3:0] $end
    $var wire 4 W! OR_OP [3:0] $end
    $var wire 4 X! XOR_OP [3:0] $end
    $var wire 4 Y! SLL_OP [3:0] $end
    $var wire 4 Z! SRL_OP [3:0] $end
    $var wire 4 [! SRA_OP [3:0] $end
    $var wire 4 \! SLT_OP [3:0] $end
    $var wire 4 ]! SLTU_OP [3:0] $end
    $var wire 32 o B_operated [31:0] $end
    $var wire 33 p add_result [32:0] $end
    $scope module FA32 $end
     $var wire 32 # A [31:0] $end
     $var wire 32 o B [31:0] $end
     $var wire 1 & cin $end
     $var wire 32 I sum [31:0] $end
     $var wire 1 r cout $end
     $var wire 33 J carry [32:0] $end
     $scope module full_adder_32bit[0] $end
      $scope module FA32 $end
       $var wire 1 ' A $end
       $var wire 1 s B $end
       $var wire 1 & cin $end
       $var wire 1 L sum $end
       $var wire 1 t cout $end
      $upscope $end
     $upscope $end
     $scope module full_adder_32bit[10] $end
      $scope module FA32 $end
       $var wire 1 ( A $end
       $var wire 1 u B $end
       $var wire 1 v cin $end
       $var wire 1 M sum $end
       $var wire 1 w cout $end
      $upscope $end
     $upscope $end
     $scope module full_adder_32bit[11] $end
      $scope module FA32 $end
       $var wire 1 ) A $end
       $var wire 1 x B $end
       $var wire 1 w cin $end
       $var wire 1 N sum $end
       $var wire 1 y cout $end
      $upscope $end
     $upscope $end
     $scope module full_adder_32bit[12] $end
      $scope module FA32 $end
       $var wire 1 * A $end
       $var wire 1 z B $end
       $var wire 1 y cin $end
       $var wire 1 O sum $end
       $var wire 1 { cout $end
      $upscope $end
     $upscope $end
     $scope module full_adder_32bit[13] $end
      $scope module FA32 $end
       $var wire 1 + A $end
       $var wire 1 | B $end
       $var wire 1 { cin $end
       $var wire 1 P sum $end
       $var wire 1 } cout $end
      $upscope $end
     $upscope $end
     $scope module full_adder_32bit[14] $end
      $scope module FA32 $end
       $var wire 1 , A $end
       $var wire 1 ~ B $end
       $var wire 1 } cin $end
       $var wire 1 Q sum $end
       $var wire 1 !! cout $end
      $upscope $end
     $upscope $end
     $scope module full_adder_32bit[15] $end
      $scope module FA32 $end
       $var wire 1 - A $end
       $var wire 1 "! B $end
       $var wire 1 !! cin $end
       $var wire 1 R sum $end
       $var wire 1 #! cout $end
      $upscope $end
     $upscope $end
     $scope module full_adder_32bit[16] $end
      $scope module FA32 $end
       $var wire 1 . A $end
       $var wire 1 $! B $end
       $var wire 1 #! cin $end
       $var wire 1 S sum $end
       $var wire 1 %! cout $end
      $upscope $end
     $upscope $end
     $scope module full_adder_32bit[17] $end
      $scope module FA32 $end
       $var wire 1 / A $end
       $var wire 1 &! B $end
       $var wire 1 %! cin $end
       $var wire 1 T sum $end
       $var wire 1 '! cout $end
      $upscope $end
     $upscope $end
     $scope module full_adder_32bit[18] $end
      $scope module FA32 $end
       $var wire 1 0 A $end
       $var wire 1 (! B $end
       $var wire 1 '! cin $end
       $var wire 1 U sum $end
       $var wire 1 )! cout $end
      $upscope $end
     $upscope $end
     $scope module full_adder_32bit[19] $end
      $scope module FA32 $end
       $var wire 1 1 A $end
       $var wire 1 *! B $end
       $var wire 1 )! cin $end
       $var wire 1 V sum $end
       $var wire 1 +! cout $end
      $upscope $end
     $upscope $end
     $scope module full_adder_32bit[1] $end
      $scope module FA32 $end
       $var wire 1 2 A $end
       $var wire 1 ,! B $end
       $var wire 1 t cin $end
       $var wire 1 W sum $end
       $var wire 1 -! cout $end
      $upscope $end
     $upscope $end
     $scope module full_adder_32bit[20] $end
      $scope module FA32 $end
       $var wire 1 3 A $end
       $var wire 1 .! B $end
       $var wire 1 +! cin $end
       $var wire 1 X sum $end
       $var wire 1 /! cout $end
      $upscope $end
     $upscope $end
     $scope module full_adder_32bit[21] $end
      $scope module FA32 $end
       $var wire 1 4 A $end
       $var wire 1 0! B $end
       $var wire 1 /! cin $end
       $var wire 1 Y sum $end
       $var wire 1 1! cout $end
      $upscope $end
     $upscope $end
     $scope module full_adder_32bit[22] $end
      $scope module FA32 $end
       $var wire 1 5 A $end
       $var wire 1 2! B $end
       $var wire 1 1! cin $end
       $var wire 1 Z sum $end
       $var wire 1 3! cout $end
      $upscope $end
     $upscope $end
     $scope module full_adder_32bit[23] $end
      $scope module FA32 $end
       $var wire 1 6 A $end
       $var wire 1 4! B $end
       $var wire 1 3! cin $end
       $var wire 1 [ sum $end
       $var wire 1 5! cout $end
      $upscope $end
     $upscope $end
     $scope module full_adder_32bit[24] $end
      $scope module FA32 $end
       $var wire 1 7 A $end
       $var wire 1 6! B $end
       $var wire 1 5! cin $end
       $var wire 1 \ sum $end
       $var wire 1 7! cout $end
      $upscope $end
     $upscope $end
     $scope module full_adder_32bit[25] $end
      $scope module FA32 $end
       $var wire 1 8 A $end
       $var wire 1 8! B $end
       $var wire 1 7! cin $end
       $var wire 1 ] sum $end
       $var wire 1 9! cout $end
      $upscope $end
     $upscope $end
     $scope module full_adder_32bit[26] $end
      $scope module FA32 $end
       $var wire 1 9 A $end
       $var wire 1 :! B $end
       $var wire 1 9! cin $end
       $var wire 1 ^ sum $end
       $var wire 1 ;! cout $end
      $upscope $end
     $upscope $end
     $scope module full_adder_32bit[27] $end
      $scope module FA32 $end
       $var wire 1 : A $end
       $var wire 1 <! B $end
       $var wire 1 ;! cin $end
       $var wire 1 _ sum $end
       $var wire 1 =! cout $end
      $upscope $end
     $upscope $end
     $scope module full_adder_32bit[28] $end
      $scope module FA32 $end
       $var wire 1 ; A $end
       $var wire 1 >! B $end
       $var wire 1 =! cin $end
       $var wire 1 ` sum $end
       $var wire 1 ?! cout $end
      $upscope $end
     $upscope $end
     $scope module full_adder_32bit[29] $end
      $scope module FA32 $end
       $var wire 1 < A $end
       $var wire 1 @! B $end
       $var wire 1 ?! cin $end
       $var wire 1 a sum $end
       $var wire 1 A! cout $end
      $upscope $end
     $upscope $end
     $scope module full_adder_32bit[2] $end
      $scope module FA32 $end
       $var wire 1 = A $end
       $var wire 1 B! B $end
       $var wire 1 -! cin $end
       $var wire 1 b sum $end
       $var wire 1 C! cout $end
      $upscope $end
     $upscope $end
     $scope module full_adder_32bit[30] $end
      $scope module FA32 $end
       $var wire 1 > A $end
       $var wire 1 D! B $end
       $var wire 1 A! cin $end
       $var wire 1 c sum $end
       $var wire 1 E! cout $end
      $upscope $end
     $upscope $end
     $scope module full_adder_32bit[31] $end
      $scope module FA32 $end
       $var wire 1 ? A $end
       $var wire 1 F! B $end
       $var wire 1 E! cin $end
       $var wire 1 d sum $end
       $var wire 1 r cout $end
      $upscope $end
     $upscope $end
     $scope module full_adder_32bit[3] $end
      $scope module FA32 $end
       $var wire 1 @ A $end
       $var wire 1 G! B $end
       $var wire 1 C! cin $end
       $var wire 1 e sum $end
       $var wire 1 H! cout $end
      $upscope $end
     $upscope $end
     $scope module full_adder_32bit[4] $end
      $scope module FA32 $end
       $var wire 1 A A $end
       $var wire 1 I! B $end
       $var wire 1 H! cin $end
       $var wire 1 f sum $end
       $var wire 1 J! cout $end
      $upscope $end
     $upscope $end
     $scope module full_adder_32bit[5] $end
      $scope module FA32 $end
       $var wire 1 B A $end
       $var wire 1 K! B $end
       $var wire 1 J! cin $end
       $var wire 1 g sum $end
       $var wire 1 L! cout $end
      $upscope $end
     $upscope $end
     $scope module full_adder_32bit[6] $end
      $scope module FA32 $end
       $var wire 1 C A $end
       $var wire 1 M! B $end
       $var wire 1 L! cin $end
       $var wire 1 h sum $end
       $var wire 1 N! cout $end
      $upscope $end
     $upscope $end
     $scope module full_adder_32bit[7] $end
      $scope module FA32 $end
       $var wire 1 D A $end
       $var wire 1 O! B $end
       $var wire 1 N! cin $end
       $var wire 1 i sum $end
       $var wire 1 P! cout $end
      $upscope $end
     $upscope $end
     $scope module full_adder_32bit[8] $end
      $scope module FA32 $end
       $var wire 1 E A $end
       $var wire 1 Q! B $end
       $var wire 1 P! cin $end
       $var wire 1 j sum $end
       $var wire 1 R! cout $end
      $upscope $end
     $upscope $end
     $scope module full_adder_32bit[9] $end
      $scope module FA32 $end
       $var wire 1 F A $end
       $var wire 1 S! B $end
       $var wire 1 R! cin $end
       $var wire 1 k sum $end
       $var wire 1 v cout $end
      $upscope $end
     $upscope $end
    $upscope $end
   $upscope $end
  $upscope $end
 $upscope $end
$enddefinitions $end


#0
b00000000000000000000000000001111 #
b00000000000000000000000000001010 $
b0000 %
0&
1'
0(
0)
0*
0+
0,
0-
0.
0/
00
01
12
03
04
05
06
07
08
09
0:
0;
0<
1=
0>
0?
1@
0A
0B
0C
0D
0E
0F
0G
0H
b00000000000000000000000000011001 I
b000000000000000000000000000011100 J
1L
0M
0N
0O
0P
0Q
0R
0S
0T
0U
0V
0W
0X
0Y
0Z
0[
0\
0]
0^
0_
0`
0a
0b
0c
0d
1e
1f
0g
0h
0i
0j
0k
b00000000000000000000000000011001 l
0m
0n
b00000000000000000000000000001010 o
b000000000000000000000000000011001 p
0r
0s
0t
0u
0v
0w
0x
0y
0z
0{
0|
0}
0~
0!!
0"!
0#!
0$!
0%!
0&!
0'!
0(!
0)!
0*!
0+!
1,!
1-!
0.!
0/!
00!
01!
02!
03!
04!
05!
06!
07!
08!
09!
0:!
0;!
0<!
0=!
0>!
0?!
0@!
0A!
0B!
1C!
0D!
0E!
0F!
1G!
1H!
0I!
0J!
0K!
0L!
0M!
0N!
0O!
0P!
0Q!
0R!
0S!
b0000 T!
b1000 U!
b0111 V!
b0110 W!
b0100 X!
b0001 Y!
b0101 Z!
b1101 [!
b0010 \!
b0011 ]!
#10
b00000000000000000000000000011001 #
b1000 %
1&
02
0=
1A
1G
b00000000000000000000000000001111 I
b111111111111111111111111111100011 J
1W
1b
0f
b00000000000000000000000000001111 l
b11111111111111111111111111110101 o
b100000000000000000000000000001111 p
1r
1s
1t
1u
1v
1w
1x
1y
1z
1{
1|
1}
1~
1!!
1"!
1#!
1$!
1%!
1&!
1'!
1(!
1)!
1*!
1+!
0,!
0-!
1.!
1/!
10!
11!
12!
13!
14!
15!
16!
17!
18!
19!
1:!
1;!
1<!
1=!
1>!
1?!
1@!
1A!
1B!
0C!
1D!
1E!
1F!
0G!
0H!
1I!
1J!
1K!
1L!
1M!
1N!
1O!
1P!
1Q!
1R!
1S!
#20
b00000000000000000000000000001100 #
b0111 %
0&
0'
1=
0A
0G
b00000000000000000000000000010110 I
b000000000000000000000000000010000 J
0L
0e
1f
b00000000000000000000000000001000 l
b00000000000000000000000000001010 o
b000000000000000000000000000010110 p
0r
0s
0t
0u
0v
0w
0x
0y
0z
0{
0|
0}
0~
0!!
0"!
0#!
0$!
0%!
0&!
0'!
0(!
0)!
0*!
0+!
1,!
0.!
0/!
00!
01!
02!
03!
04!
05!
06!
07!
08!
09!
0:!
0;!
0<!
0=!
0>!
0?!
0@!
0A!
0B!
0D!
0E!
0F!
1G!
1H!
0I!
0J!
0K!
0L!
0M!
0N!
0O!
0P!
0Q!
0R!
0S!
#30
b0110 %
b00000000000000000000000000001110 l
#40
b0100 %
b00000000000000000000000000000110 l
#50
b00000000000000000000000000001111 #
b00000000000000000000000000000010 $
b0001 %
1'
12
b00000000000000000000000000010001 I
b000000000000000000000000000011100 J
1L
0W
0b
b00000000000000000000000000111100 l
b00000000000000000000000000000010 o
b000000000000000000000000000010001 p
1-!
1C!
0G!
#60
b11111111111111111111111111111011 #
b00000000000000000000000000001010 $
b0010 %
1(
1)
1*
1+
1,
1-
1.
1/
10
11
13
14
15
16
17
18
19
1:
1;
1<
0=
1>
1?
1A
1B
1C
1D
1E
1F
b00000000000000000000000000000101 I
b111111111111111111111111111110100 J
1b
0f
b00000000000000000000000000000001 l
b00000000000000000000000000001010 o
b100000000000000000000000000000101 p
1r
1v
1w
1y
1{
1}
1!!
1#!
1%!
1'!
1)!
1+!
1/!
11!
13!
15!
17!
19!
1;!
1=!
1?!
1A!
0C!
1E!
1G!
1J!
1L!
1N!
1P!
1R!
#70
b00000000000000000000000000101010 #
b00000000000000000000000000101010 $
b1000 %
1&
0'
0(
0)
0*
0+
0,
0-
0.
0/
00
01
03
04
05
06
07
08
09
0:
0;
0<
0>
0?
0A
0C
0D
0E
0F
1G
b00000000000000000000000000000000 I
b111111111111111111111111111111111 J
0L
0b
b00000000000000000000000000000000 l
1m
b11111111111111111111111111010101 o
b100000000000000000000000000000000 p
1s
1t
1u
1x
1z
1|
1~
1"!
1$!
1&!
1(!
1*!
0,!
1.!
10!
12!
14!
16!
18!
1:!
1<!
1>!
1@!
1B!
1C!
1D!
1F!
0G!
1I!
1M!
1O!
1Q!
1S!
